fiblary3/__init__.py
fiblary3/client/__init__.py
fiblary3/client/v3/__init__.py
fiblary3/client/v3/base.py
fiblary3/client/v3/client.py
fiblary3/client/v3/devices.py
fiblary3/client/v3/events.py
fiblary3/client/v3/info.py
fiblary3/client/v3/login.py
fiblary3/client/v3/models.py
fiblary3/client/v3/rooms.py
fiblary3/client/v3/scenes.py
fiblary3/client/v3/sections.py
fiblary3/client/v3/users.py
fiblary3/client/v3/variables.py
fiblary3/client/v3/weather.py
fiblary3/client/v4/__init__.py
fiblary3/client/v4/base.py
fiblary3/client/v4/client.py
fiblary3/client/v4/devices.py
fiblary3/client/v4/events.py
fiblary3/client/v4/info.py
fiblary3/client/v4/login.py
fiblary3/client/v4/models.py
fiblary3/client/v4/rooms.py
fiblary3/client/v4/scenes.py
fiblary3/client/v4/sections.py
fiblary3/client/v4/users.py
fiblary3/client/v4/variables.py
fiblary3/client/v4/weather.py
fiblary3/client/v5/__init__.py
fiblary3/client/v5/base.py
fiblary3/client/v5/client.py
fiblary3/client/v5/devices.py
fiblary3/client/v5/events.py
fiblary3/client/v5/info.py
fiblary3/client/v5/login.py
fiblary3/client/v5/models.py
fiblary3/client/v5/rooms.py
fiblary3/client/v5/scenes.py
fiblary3/client/v5/sections.py
fiblary3/client/v5/users.py
fiblary3/client/v5/variables.py
fiblary3/client/v5/weather.py
fiblary3/common/__init__.py
fiblary3/common/beacon.py
fiblary3/common/event.py
fiblary3/common/exceptions.py
fiblary3/common/net.py
fiblary3/common/restapi.py
fiblary3/common/timestamp.py
fiblary3/common/utils.py
fiblary3/external/__init__.py
fiblary3/external/jsonpath.py
fiblary3/tests/__init__.py
fiblary3/tests/utils.py
fiblary3/tests/unit/__init__.py
fiblary3/tests/unit/test_event.py
fiblary3/tests/unit/test_restapi.py
fiblary3/tests/unit/test_timestamp.py
fiblary3/tests/unit/test_utils.py
fiblary3_fork-0.1.12.dist-info/AUTHORS
fiblary3_fork-0.1.12.dist-info/LICENSE
fiblary3_fork-0.1.12.dist-info/METADATA
fiblary3_fork-0.1.12.dist-info/WHEEL
fiblary3_fork-0.1.12.dist-info/top_level.txt
fiblary3_fork-0.1.12.dist-info/RECORD
