Metadata-Version: 2.1
Name: fiblary3-fork
Version: 0.1.12
Summary: Home Center API Python Library - forked version
Home-page: https://github.com/graham33/fiblary
Author: Peter Balogh, Graham Bennett
Author-email: graham@grahambennett.org
License: Apache 2.0
Platform: UNKNOWN
Classifier: Development Status :: 5 - Production/Stable
Classifier: Intended Audience :: Developers
Classifier: Natural Language :: English
Classifier: License :: OSI Approved :: Apache Software License
Classifier: Operating System :: POSIX :: Linux
Classifier: Programming Language :: Python
Classifier: Programming Language :: Python :: 3
License-File: LICENSE
License-File: AUTHORS
Requires-Dist: jsonpatch
Requires-Dist: netaddr
Requires-Dist: prettytable
Requires-Dist: python-dateutil
Requires-Dist: requests
Requires-Dist: six
